mlops/__init__.py
mlops/artifact/__init__.py
mlops/artifact/versioned_artifact.py
mlops/artifact/versioned_artifact_builder.py
mlops/dataset/__init__.py
mlops/dataset/data_processor.py
mlops/dataset/invertible_data_processor.py
mlops/dataset/pathless_data_processor.py
mlops/dataset/pathless_versioned_dataset_builder.py
mlops/dataset/versioned_dataset.py
mlops/dataset/versioned_dataset_builder.py
mlops/errors/__init__.py
mlops/examples/__init__.py
mlops/examples/image/__init__.py
mlops/examples/image/classification/__init__.py
mlops/examples/image/classification/errors.py
mlops/examples/image/classification/model_prediction.py
mlops/examples/image/classification/pokemon_classification_data_processor.py
mlops/examples/image/classification/publish_dataset.py
mlops/examples/image/classification/train_model.py
mlops/hashing/__init__.py
mlops/hashing/hashing.py
mlops/model/__init__.py
mlops/model/training_config.py
mlops/model/versioned_model.py
mlops/model/versioned_model_builder.py
mloperations-0.1.7.dist-info/LICENSE
mloperations-0.1.7.dist-info/METADATA
mloperations-0.1.7.dist-info/WHEEL
mloperations-0.1.7.dist-info/top_level.txt
mloperations-0.1.7.dist-info/RECORD
