Metadata-Version: 2.1
Name: mloperations
Version: 0.1.7
Summary: A framework for conducting MLOps.
Home-page: https://github.com/kostaleonard/mlops
Author: Leo Kosta
Author-email: kostaleonard@gmail.com
License: UNKNOWN
Project-URL: Bug Tracker, https://github.com/kostaleonard/mlops/issues
Platform: UNKNOWN
Classifier: Programming Language :: Python :: 3
Classifier: License :: OSI Approved :: MIT License
Classifier: Operating System :: OS Independent
License-File: LICENSE
Requires-Dist: numpy
Requires-Dist: s3fs
Requires-Dist: dill
Requires-Dist: tensorflow
